jupyter_videochat/__init__.py
jupyter_videochat/_version.py
jupyter_videochat/handlers.py
jupyter_videochat/labextension/package.json
jupyter_videochat/labextension/schemas/jupyterlab-videochat/package.json.orig
jupyter_videochat/labextension/schemas/jupyterlab-videochat/plugin.json
jupyter_videochat/labextension/static/549.5e91e6d68be345c73122.js
jupyter_videochat/labextension/static/568.2bbf7fa8f71427f55bf0.js
jupyter_videochat/labextension/static/872.18aa65c166b896557351.js
jupyter_videochat/labextension/static/remoteEntry.e46323a1758c0d1ceffb.js
jupyter_videochat/labextension/static/style.js
jupyter_videochat/labextension/static/third-party-licenses.json
jupyter_videochat-0.6.0.data/data/etc/jupyter/jupyter_notebook_config.d/jupyter_videochat.json
jupyter_videochat-0.6.0.data/data/etc/jupyter/jupyter_server_config.d/jupyter_videochat.json
jupyter_videochat-0.6.0.data/data/share/jupyter/labextensions/jupyterlab-videochat/install.json
jupyter_videochat-0.6.0.data/data/share/jupyter/labextensions/jupyterlab-videochat/package.json
jupyter_videochat-0.6.0.data/data/share/jupyter/labextensions/jupyterlab-videochat/schemas/jupyterlab-videochat/package.json.orig
jupyter_videochat-0.6.0.data/data/share/jupyter/labextensions/jupyterlab-videochat/schemas/jupyterlab-videochat/plugin.json
jupyter_videochat-0.6.0.data/data/share/jupyter/labextensions/jupyterlab-videochat/static/549.5e91e6d68be345c73122.js
jupyter_videochat-0.6.0.data/data/share/jupyter/labextensions/jupyterlab-videochat/static/568.2bbf7fa8f71427f55bf0.js
jupyter_videochat-0.6.0.data/data/share/jupyter/labextensions/jupyterlab-videochat/static/872.18aa65c166b896557351.js
jupyter_videochat-0.6.0.data/data/share/jupyter/labextensions/jupyterlab-videochat/static/remoteEntry.e46323a1758c0d1ceffb.js
jupyter_videochat-0.6.0.data/data/share/jupyter/labextensions/jupyterlab-videochat/static/style.js
jupyter_videochat-0.6.0.data/data/share/jupyter/labextensions/jupyterlab-videochat/static/third-party-licenses.json
jupyter_videochat-0.6.0.dist-info/LICENSE
jupyter_videochat-0.6.0.dist-info/METADATA
jupyter_videochat-0.6.0.dist-info/WHEEL
jupyter_videochat-0.6.0.dist-info/top_level.txt
jupyter_videochat-0.6.0.dist-info/RECORD
