Metadata-Version: 2.1
Name: jupyter-videochat
Version: 0.6.0
Summary: Video Chat with peers inside JupyterLab and RetroLab
Home-page: https://github.com/jupyterlab-contrib/jupyter-videochat
Author: Yuvi Panda
License: BSD-3-Clause
Project-URL: Bug Tracker, https://github.com/jupyterlab-contrib/jupyter-videochat/issues
Project-URL: Source Code, https://github.com/jupyterlab-contrib/jupyter-videochat.git
Keywords: Jupyter,JupyterLab
Platform: UNKNOWN
Classifier: Intended Audience :: Developers
Classifier: License :: OSI Approved :: BSD License
Classifier: Programming Language :: Python
Classifier: Programming Language :: Python :: 3
Classifier: Framework :: Jupyter
Classifier: Framework :: Jupyter :: JupyterLab
Classifier: Framework :: Jupyter :: JupyterLab :: 3
Classifier: Framework :: Jupyter :: JupyterLab :: Extensions
Classifier: Framework :: Jupyter :: JupyterLab :: Extensions :: Prebuilt
Requires-Python: >=3.7
License-File: LICENSE
Requires-Dist: jupyter-server
Requires-Dist: escapism
Provides-Extra: docs
Requires-Dist: jupyterlab (==3.*) ; extra == 'docs'
Requires-Dist: ipywidgets ; extra == 'docs'
Requires-Dist: jupyterlite (==0.1.0b4) ; extra == 'docs'
Requires-Dist: myst-nb ; extra == 'docs'
Requires-Dist: pydata-sphinx-theme ; extra == 'docs'
Requires-Dist: pytest-check-links ; extra == 'docs'
Requires-Dist: retrolab (>=0.3.20) ; extra == 'docs'
Requires-Dist: sphinx ; extra == 'docs'
Requires-Dist: sphinx-jsonschema ; extra == 'docs'
Provides-Extra: lab
Requires-Dist: jupyterlab (==3.*) ; extra == 'lab'
Provides-Extra: lint
Requires-Dist: jupyterlab (==3.*) ; extra == 'lint'
Requires-Dist: isort ; extra == 'lint'
Requires-Dist: black (==22.3.0) ; extra == 'lint'
